nexstar/__init__.py
nexstar-0.0.4.dist-info/LICENSE
nexstar-0.0.4.dist-info/METADATA
nexstar-0.0.4.dist-info/WHEEL
nexstar-0.0.4.dist-info/top_level.txt
nexstar-0.0.4.dist-info/RECORD
