Metadata-Version: 2.1
Name: nexstar
Version: 0.0.4
Summary: Python interface for Celestron Nexstar telescopes
Home-page: https://github.com/circuitqed/nexstar
Author: David Schuster
Author-email: David.Schuster@gmail.com
License: UNKNOWN
Platform: UNKNOWN
Classifier: Programming Language :: Python :: 3
Classifier: License :: OSI Approved :: MIT License
Classifier: Operating System :: OS Independent
Requires-Dist: pyserial
Requires-Dist: pytz
